pretty_admin/__init__.py
pretty_admin/admin.py
pretty_admin/apps.py
pretty_admin/models.py
pretty_admin/tests.py
pretty_admin/views.py
pretty_admin/migrations/__init__.py
pretty_admin/static/pretty_admin/css/tailwind.js
pretty_admin/templates/admin/404.html
pretty_admin/templates/admin/500.html
pretty_admin/templates/admin/actions.html
pretty_admin/templates/admin/app_index.html
pretty_admin/templates/admin/app_list.html
pretty_admin/templates/admin/base.html
pretty_admin/templates/admin/base_login.html
pretty_admin/templates/admin/base_site.html
pretty_admin/templates/admin/change_form.html
pretty_admin/templates/admin/change_form_object_tools.html
pretty_admin/templates/admin/change_list.html
pretty_admin/templates/admin/change_list_object_tools.html
pretty_admin/templates/admin/change_list_results.html
pretty_admin/templates/admin/color_theme_toggle.html
pretty_admin/templates/admin/date_hierarchy.html
pretty_admin/templates/admin/delete_confirmation.html
pretty_admin/templates/admin/delete_selected_confirmation.html
pretty_admin/templates/admin/filter.html
pretty_admin/templates/admin/index.html
pretty_admin/templates/admin/invalid_setup.html
pretty_admin/templates/admin/login.html
pretty_admin/templates/admin/nav_sidebar.html
pretty_admin/templates/admin/object_history.html
pretty_admin/templates/admin/pagination.html
pretty_admin/templates/admin/popup_response.html
pretty_admin/templates/admin/prepopulated_fields_js.html
pretty_admin/templates/admin/search_form.html
pretty_admin/templates/admin/submit_line.html
pretty_admin/templates/admin/auth/user/add_form.html
pretty_admin/templates/admin/auth/user/change_password.html
pretty_admin/templates/admin/edit_inline/stacked.html
pretty_admin/templates/admin/edit_inline/tabular.html
pretty_admin/templates/admin/includes/fieldset.html
pretty_admin/templates/admin/includes/object_delete_summary.html
pretty_admin/templates/admin/widgets/clearable_file_input.html
pretty_admin/templates/admin/widgets/date.html
pretty_admin-0.1.5.dist-info/METADATA
pretty_admin-0.1.5.dist-info/WHEEL
pretty_admin-0.1.5.dist-info/top_level.txt
pretty_admin-0.1.5.dist-info/RECORD
