Metadata-Version: 2.1
Name: pretty-admin
Version: 0.1.5
Summary: A Tailwind-based Django admin UI skin
Home-page: https://github.com/Pruthvi2121/pretty_admin
Author: Pruthviraj Chokake
Author-email: chokake.pruthvi@gmail.com
License: MIT
Project-URL: Homepage, https://github.com/Pruthvi2121/pretty_admin
Project-URL: Bug Tracker, https://github.com/Pruthvi2121/pretty_admin/issues
Platform: UNKNOWN
Classifier: Development Status :: 4 - Beta
Classifier: Framework :: Django
Classifier: Intended Audience :: Developers
Classifier: License :: OSI Approved :: MIT License
Classifier: Programming Language :: Python :: 3
Classifier: Operating System :: OS Independent
Requires-Python: >=3.6
Requires-Dist: Django>=3.2
Requires-Dist: setuptools
